README.rst
setup.py
ld/__init__.py
ld/constants.py
ld.egg-info/PKG-INFO
ld.egg-info/SOURCES.txt
ld.egg-info/dependency_links.txt
ld.egg-info/requires.txt
ld.egg-info/top_level.txt