Metadata-Version: 1.1
Name: ld
Version: 0.5.0
Summary: Linux Distribution - a Linux OS platform information API
Home-page: https://github.com/nir0s/ld
Author: Nir Cohen
Author-email: nir36g@gmail.com
License: Apache License, Version 2.0
Platform: All
Classifier: Development Status :: 4 - Beta
Classifier: Intended Audience :: Developers
Classifier: License :: OSI Approved :: Apache Software License
Classifier: Operating System :: OS Independent
Classifier: Programming Language :: Python :: 2.6
Classifier: Programming Language :: Python :: 2.7
Classifier: Programming Language :: Python :: 3.4
Classifier: Programming Language :: Python :: 3.5
Classifier: Topic :: Software Development :: Libraries :: Python Modules
Classifier: Topic :: System :: Operating System
